arqueue.py
ARQueue-1.2.0.data/data/.env.sample
ARQueue-1.2.0.dist-info/LICENSE
ARQueue-1.2.0.dist-info/METADATA
ARQueue-1.2.0.dist-info/WHEEL
ARQueue-1.2.0.dist-info/entry_points.txt
ARQueue-1.2.0.dist-info/top_level.txt
ARQueue-1.2.0.dist-info/RECORD
